weiss_sim-0.1.3.dist-info/METADATA
weiss_sim-0.1.3.dist-info/WHEEL
weiss_sim/__init__.py
weiss_sim/rl.py
weiss_sim/weiss_sim.cpython-311-darwin.so
weiss_sim-0.1.3.dist-info/RECORD
