Metadata-Version: 2.4
Name: weiss-sim
Version: 0.1.3
Classifier: Development Status :: 3 - Alpha
Classifier: Intended Audience :: Developers
Classifier: License :: OSI Approved :: MIT License
Classifier: License :: OSI Approved :: Apache Software License
Classifier: Operating System :: OS Independent
Classifier: Programming Language :: Python :: 3
Classifier: Programming Language :: Python :: 3 :: Only
Classifier: Programming Language :: Rust
Classifier: Topic :: Games/Entertainment
Classifier: Topic :: Scientific/Engineering :: Artificial Intelligence
Requires-Dist: numpy>=1.23
Summary: Deterministic Weiss Schwarz simulator with a Rust core and Python bindings.
Keywords: weiss-schwarz,reinforcement-learning,simulation,pyo3,rl
Author: Lallan
License: MIT OR Apache-2.0
Requires-Python: >=3.10
Project-URL: Homepage, https://github.com/victorwp288/weiss-schwarz-simulator
Project-URL: Repository, https://github.com/victorwp288/weiss-schwarz-simulator
Project-URL: Documentation, https://victorwp288.github.io/weiss-schwarz-simulator/rustdoc/
Project-URL: Issues, https://github.com/victorwp288/weiss-schwarz-simulator/issues
Project-URL: Changelog, https://github.com/victorwp288/weiss-schwarz-simulator/blob/main/CHANGELOG.md
